<?xml version="1.0" encoding="utf-8"?>
<REQ-IF p1:lang="en" xmlns:p1="xml" xmlns="http://www.omg.org/spec/ReqIF/20110401/reqif.xsd">
  <THE-HEADER>
    <REQ-IF-HEADER IDENTIFIER="15580898-fb17-43d3-9d0a-b2ae8a7986ea">
      <CREATION-TIME>2022-01-10T09:24:18.8831825Z</CREATION-TIME>
      <REQ-IF-TOOL-ID>COMET</REQ-IF-TOOL-ID>
      <REQ-IF-VERSION />
      <SOURCE-TOOL-ID>COMET</SOURCE-TOOL-ID>
      <TITLE> ()</TITLE>
    </REQ-IF-HEADER>
  </THE-HEADER>
  <CORE-CONTENT>
    <REQ-IF-CONTENT>
      <DATATYPES>
        <DATATYPE-DEFINITION-BOOLEAN DESC="bool" IDENTIFIER="9b2e4528-dcb9-4429-841b-f0b840b15e13" LAST-CHANGE="2022-01-10T09:24:18.8850584Z" LONG-NAME="bool" />
        <DATATYPE-DEFINITION-STRING MAX-LENGTH="0" DESC="A string datatype" IDENTIFIER="a0788043-3c29-4cdc-b656-816a1a9e111d" LAST-CHANGE="2022-01-10T09:24:18.8831825Z" LONG-NAME="String" />
        <DATATYPE-DEFINITION-BOOLEAN DESC="A boolean datatype" IDENTIFIER="cf78e807-a8af-4816-aa0f-c7b9e7ec1520" LAST-CHANGE="2022-01-10T10:24:18.8831825+01:00" LONG-NAME="Boolean" />
      </DATATYPES>
      <SPEC-TYPES>
        <SPECIFICATION-TYPE DESC="RequirementsSpecification" IDENTIFIER="a2502760-9a0d-47c3-85b8-eaade10bd657" LAST-CHANGE="2022-01-10T09:24:18.8935438Z" LONG-NAME="RequirementsSpecification">
          <SPEC-ATTRIBUTES>
            <ATTRIBUTE-DEFINITION-STRING DESC="The Short-Name Attribute" IDENTIFIER="4e508b19-4c5d-408d-a8f1-c465b34714f6" LAST-CHANGE="2022-01-10T09:24:18.8935438Z" LONG-NAME="Short-Name">
              <TYPE>
                <DATATYPE-DEFINITION-STRING-REF>a0788043-3c29-4cdc-b656-816a1a9e111d</DATATYPE-DEFINITION-STRING-REF>
              </TYPE>
            </ATTRIBUTE-DEFINITION-STRING>
            <ATTRIBUTE-DEFINITION-STRING DESC="The Name Attribute" IDENTIFIER="466dbc5f-18a6-433e-b2c4-46f82fc5a360" LAST-CHANGE="2022-01-10T09:24:18.8935438Z" LONG-NAME="Name">
              <TYPE>
                <DATATYPE-DEFINITION-STRING-REF>a0788043-3c29-4cdc-b656-816a1a9e111d</DATATYPE-DEFINITION-STRING-REF>
              </TYPE>
            </ATTRIBUTE-DEFINITION-STRING>
            <ATTRIBUTE-DEFINITION-STRING DESC="The Categories Attribute" IDENTIFIER="01fd8f87-b4d3-421b-9419-ad4b46fa6a0d" LAST-CHANGE="2022-01-10T09:24:18.8935438Z" LONG-NAME="Categories">
              <TYPE>
                <DATATYPE-DEFINITION-STRING-REF>a0788043-3c29-4cdc-b656-816a1a9e111d</DATATYPE-DEFINITION-STRING-REF>
              </TYPE>
            </ATTRIBUTE-DEFINITION-STRING>
            <ATTRIBUTE-DEFINITION-BOOLEAN DESC="The IsDeprecated Attribute Definition" IDENTIFIER="ee2625f8-c6d5-4543-a81d-b949aefd0d33" LAST-CHANGE="2022-01-10T10:24:18.8935438+01:00" LONG-NAME="IsDeprecated">
              <TYPE>
                <DATATYPE-DEFINITION-BOOLEAN-REF>cf78e807-a8af-4816-aa0f-c7b9e7ec1520</DATATYPE-DEFINITION-BOOLEAN-REF>
              </TYPE>
            </ATTRIBUTE-DEFINITION-BOOLEAN>
          </SPEC-ATTRIBUTES>
        </SPECIFICATION-TYPE>
        <SPEC-OBJECT-TYPE DESC="RequirementsGroup" IDENTIFIER="caed1125-eab0-4778-8f33-43100e3d08b9" LAST-CHANGE="2022-01-10T09:24:18.8965904Z" LONG-NAME="[Group]RequirementsGroup">
          <SPEC-ATTRIBUTES>
            <ATTRIBUTE-DEFINITION-STRING DESC="The Short-Name Attribute" IDENTIFIER="bd064023-6698-4691-9245-ae7f481188bd" LAST-CHANGE="2022-01-10T09:24:18.8965904Z" LONG-NAME="Short-Name">
              <TYPE>
                <DATATYPE-DEFINITION-STRING-REF>a0788043-3c29-4cdc-b656-816a1a9e111d</DATATYPE-DEFINITION-STRING-REF>
              </TYPE>
            </ATTRIBUTE-DEFINITION-STRING>
            <ATTRIBUTE-DEFINITION-STRING DESC="The Name Attribute" IDENTIFIER="d3036868-ad6f-49cd-ab3e-011ad4305750" LAST-CHANGE="2022-01-10T09:24:18.8965904Z" LONG-NAME="Name">
              <TYPE>
                <DATATYPE-DEFINITION-STRING-REF>a0788043-3c29-4cdc-b656-816a1a9e111d</DATATYPE-DEFINITION-STRING-REF>
              </TYPE>
            </ATTRIBUTE-DEFINITION-STRING>
            <ATTRIBUTE-DEFINITION-STRING DESC="The Categories Attribute" IDENTIFIER="db8bd8d2-445b-4330-a76d-797aa23da207" LAST-CHANGE="2022-01-10T09:24:18.8965904Z" LONG-NAME="Categories">
              <TYPE>
                <DATATYPE-DEFINITION-STRING-REF>a0788043-3c29-4cdc-b656-816a1a9e111d</DATATYPE-DEFINITION-STRING-REF>
              </TYPE>
            </ATTRIBUTE-DEFINITION-STRING>
          </SPEC-ATTRIBUTES>
        </SPEC-OBJECT-TYPE>
        <SPEC-OBJECT-TYPE DESC="param Rule" IDENTIFIER="aed25a8c-2542-4d63-8554-c35339b6a343" LAST-CHANGE="2022-01-10T09:24:18.8985401Z" LONG-NAME="ParamRule">
          <SPEC-ATTRIBUTES>
            <ATTRIBUTE-DEFINITION-STRING DESC="The Short-Name Attribute" IDENTIFIER="25bdbfa1-7c34-4957-86d8-f60b0bae1271" LAST-CHANGE="2022-01-10T09:24:18.8985401Z" LONG-NAME="Short-Name">
              <TYPE>
                <DATATYPE-DEFINITION-STRING-REF>a0788043-3c29-4cdc-b656-816a1a9e111d</DATATYPE-DEFINITION-STRING-REF>
              </TYPE>
            </ATTRIBUTE-DEFINITION-STRING>
            <ATTRIBUTE-DEFINITION-STRING DESC="The Name Attribute" IDENTIFIER="44141c10-7c6f-463a-8f51-d195bf21d564" LAST-CHANGE="2022-01-10T09:24:18.8985401Z" LONG-NAME="Name">
              <TYPE>
                <DATATYPE-DEFINITION-STRING-REF>a0788043-3c29-4cdc-b656-816a1a9e111d</DATATYPE-DEFINITION-STRING-REF>
              </TYPE>
            </ATTRIBUTE-DEFINITION-STRING>
            <ATTRIBUTE-DEFINITION-STRING DESC="The Categories Attribute" IDENTIFIER="1ac69cba-68c9-4fd3-858a-fd0466a86a5d" LAST-CHANGE="2022-01-10T09:24:18.8985401Z" LONG-NAME="Categories">
              <TYPE>
                <DATATYPE-DEFINITION-STRING-REF>a0788043-3c29-4cdc-b656-816a1a9e111d</DATATYPE-DEFINITION-STRING-REF>
              </TYPE>
            </ATTRIBUTE-DEFINITION-STRING>
            <ATTRIBUTE-DEFINITION-STRING DESC="The Requirement Text Attribute Definition" IDENTIFIER="7dd4fecf-4848-49b5-8f6d-5366bbc35491" LAST-CHANGE="2022-01-10T09:24:18.8985401Z" LONG-NAME="Requirement Text">
              <TYPE>
                <DATATYPE-DEFINITION-STRING-REF>a0788043-3c29-4cdc-b656-816a1a9e111d</DATATYPE-DEFINITION-STRING-REF>
              </TYPE>
            </ATTRIBUTE-DEFINITION-STRING>
            <ATTRIBUTE-DEFINITION-BOOLEAN DESC="The IsDeprecated Attribute Definition" IDENTIFIER="58535613-e8d1-4884-a96c-c226680ed04a" LAST-CHANGE="2022-01-10T10:24:18.8985401+01:00" LONG-NAME="IsDeprecated">
              <TYPE>
                <DATATYPE-DEFINITION-BOOLEAN-REF>cf78e807-a8af-4816-aa0f-c7b9e7ec1520</DATATYPE-DEFINITION-BOOLEAN-REF>
              </TYPE>
            </ATTRIBUTE-DEFINITION-BOOLEAN>
            <ATTRIBUTE-DEFINITION-BOOLEAN DESC="-" IDENTIFIER="6528c6b6-e10d-4170-b003-2940dfaf7ae8" LAST-CHANGE="2022-01-10T10:24:18.8995922+01:00">
              <TYPE>
                <DATATYPE-DEFINITION-BOOLEAN-REF>9b2e4528-dcb9-4429-841b-f0b840b15e13</DATATYPE-DEFINITION-BOOLEAN-REF>
              </TYPE>
            </ATTRIBUTE-DEFINITION-BOOLEAN>
          </SPEC-ATTRIBUTES>
        </SPEC-OBJECT-TYPE>
        <SPEC-OBJECT-TYPE DESC="param Rule" IDENTIFIER="dcfb10da-c1ae-4dc4-904c-1c12b0d0647f" LAST-CHANGE="2022-01-10T09:24:18.8995922Z" LONG-NAME="ParamRule">
          <SPEC-ATTRIBUTES>
            <ATTRIBUTE-DEFINITION-STRING DESC="The Short-Name Attribute" IDENTIFIER="526d8c4a-f1a2-46c1-a561-183d65d42a08" LAST-CHANGE="2022-01-10T09:24:18.8995922Z" LONG-NAME="Short-Name">
              <TYPE>
                <DATATYPE-DEFINITION-STRING-REF>a0788043-3c29-4cdc-b656-816a1a9e111d</DATATYPE-DEFINITION-STRING-REF>
              </TYPE>
            </ATTRIBUTE-DEFINITION-STRING>
            <ATTRIBUTE-DEFINITION-STRING DESC="The Name Attribute" IDENTIFIER="6bf9b5ae-c23a-4499-998f-691e3533dde5" LAST-CHANGE="2022-01-10T09:24:18.8995922Z" LONG-NAME="Name">
              <TYPE>
                <DATATYPE-DEFINITION-STRING-REF>a0788043-3c29-4cdc-b656-816a1a9e111d</DATATYPE-DEFINITION-STRING-REF>
              </TYPE>
            </ATTRIBUTE-DEFINITION-STRING>
            <ATTRIBUTE-DEFINITION-STRING DESC="The Categories Attribute" IDENTIFIER="13b519fe-1bac-4d76-96a3-1f34a1a31b29" LAST-CHANGE="2022-01-10T09:24:18.8995922Z" LONG-NAME="Categories">
              <TYPE>
                <DATATYPE-DEFINITION-STRING-REF>a0788043-3c29-4cdc-b656-816a1a9e111d</DATATYPE-DEFINITION-STRING-REF>
              </TYPE>
            </ATTRIBUTE-DEFINITION-STRING>
            <ATTRIBUTE-DEFINITION-STRING DESC="The Requirement Text Attribute Definition" IDENTIFIER="e0a57b4f-e2a1-4597-8b6c-03d91a493450" LAST-CHANGE="2022-01-10T09:24:18.8995922Z" LONG-NAME="Requirement Text">
              <TYPE>
                <DATATYPE-DEFINITION-STRING-REF>a0788043-3c29-4cdc-b656-816a1a9e111d</DATATYPE-DEFINITION-STRING-REF>
              </TYPE>
            </ATTRIBUTE-DEFINITION-STRING>
            <ATTRIBUTE-DEFINITION-BOOLEAN DESC="The IsDeprecated Attribute Definition" IDENTIFIER="a63fdc2f-4958-44ac-bb18-1cc67e4be64f" LAST-CHANGE="2022-01-10T10:24:18.8995922+01:00" LONG-NAME="IsDeprecated">
              <TYPE>
                <DATATYPE-DEFINITION-BOOLEAN-REF>cf78e807-a8af-4816-aa0f-c7b9e7ec1520</DATATYPE-DEFINITION-BOOLEAN-REF>
              </TYPE>
            </ATTRIBUTE-DEFINITION-BOOLEAN>
            <ATTRIBUTE-DEFINITION-BOOLEAN DESC="-" IDENTIFIER="923d214a-e31b-42fb-8ae7-7acc5067de99" LAST-CHANGE="2022-01-10T10:24:18.8995922+01:00">
              <TYPE>
                <DATATYPE-DEFINITION-BOOLEAN-REF>9b2e4528-dcb9-4429-841b-f0b840b15e13</DATATYPE-DEFINITION-BOOLEAN-REF>
              </TYPE>
            </ATTRIBUTE-DEFINITION-BOOLEAN>
          </SPEC-ATTRIBUTES>
        </SPEC-OBJECT-TYPE>
        <SPEC-OBJECT-TYPE DESC="param Rule" IDENTIFIER="5e3b473a-588b-41d2-ab31-7235efffce01" LAST-CHANGE="2022-01-10T09:24:18.8995922Z" LONG-NAME="ParamRule">
          <SPEC-ATTRIBUTES>
            <ATTRIBUTE-DEFINITION-STRING DESC="The Short-Name Attribute" IDENTIFIER="94a83ce4-eac5-4b9f-8e50-0fdb3d61c47e" LAST-CHANGE="2022-01-10T09:24:18.8995922Z" LONG-NAME="Short-Name">
              <TYPE>
                <DATATYPE-DEFINITION-STRING-REF>a0788043-3c29-4cdc-b656-816a1a9e111d</DATATYPE-DEFINITION-STRING-REF>
              </TYPE>
            </ATTRIBUTE-DEFINITION-STRING>
            <ATTRIBUTE-DEFINITION-STRING DESC="The Name Attribute" IDENTIFIER="196ddc91-515d-4505-8b84-4766e7fa1494" LAST-CHANGE="2022-01-10T09:24:18.8995922Z" LONG-NAME="Name">
              <TYPE>
                <DATATYPE-DEFINITION-STRING-REF>a0788043-3c29-4cdc-b656-816a1a9e111d</DATATYPE-DEFINITION-STRING-REF>
              </TYPE>
            </ATTRIBUTE-DEFINITION-STRING>
            <ATTRIBUTE-DEFINITION-STRING DESC="The Categories Attribute" IDENTIFIER="5deaa9c8-276c-45c5-9ce1-0a3bf50885a3" LAST-CHANGE="2022-01-10T09:24:18.8995922Z" LONG-NAME="Categories">
              <TYPE>
                <DATATYPE-DEFINITION-STRING-REF>a0788043-3c29-4cdc-b656-816a1a9e111d</DATATYPE-DEFINITION-STRING-REF>
              </TYPE>
            </ATTRIBUTE-DEFINITION-STRING>
            <ATTRIBUTE-DEFINITION-STRING DESC="The Requirement Text Attribute Definition" IDENTIFIER="052c30a1-7ab1-4bd3-957c-a951b03a4256" LAST-CHANGE="2022-01-10T09:24:18.8995922Z" LONG-NAME="Requirement Text">
              <TYPE>
                <DATATYPE-DEFINITION-STRING-REF>a0788043-3c29-4cdc-b656-816a1a9e111d</DATATYPE-DEFINITION-STRING-REF>
              </TYPE>
            </ATTRIBUTE-DEFINITION-STRING>
            <ATTRIBUTE-DEFINITION-BOOLEAN DESC="The IsDeprecated Attribute Definition" IDENTIFIER="fa6b0289-94f9-470e-958f-3ca1a700038f" LAST-CHANGE="2022-01-10T10:24:18.8995922+01:00" LONG-NAME="IsDeprecated">
              <TYPE>
                <DATATYPE-DEFINITION-BOOLEAN-REF>cf78e807-a8af-4816-aa0f-c7b9e7ec1520</DATATYPE-DEFINITION-BOOLEAN-REF>
              </TYPE>
            </ATTRIBUTE-DEFINITION-BOOLEAN>
            <ATTRIBUTE-DEFINITION-BOOLEAN DESC="-" IDENTIFIER="ced1aa61-c151-476a-aada-78de522bc33e" LAST-CHANGE="2022-01-10T10:24:18.8995922+01:00">
              <TYPE>
                <DATATYPE-DEFINITION-BOOLEAN-REF>9b2e4528-dcb9-4429-841b-f0b840b15e13</DATATYPE-DEFINITION-BOOLEAN-REF>
              </TYPE>
            </ATTRIBUTE-DEFINITION-BOOLEAN>
          </SPEC-ATTRIBUTES>
        </SPEC-OBJECT-TYPE>
        <SPEC-OBJECT-TYPE DESC="param Rule" IDENTIFIER="ac4d80e2-55b7-4447-8a17-f5409b712931" LAST-CHANGE="2022-01-10T09:24:18.8995922Z" LONG-NAME="ParamRule">
          <SPEC-ATTRIBUTES>
            <ATTRIBUTE-DEFINITION-STRING DESC="The Short-Name Attribute" IDENTIFIER="c71bcd70-44e9-4ba7-b5a2-c6acbfd9dfea" LAST-CHANGE="2022-01-10T09:24:18.8995922Z" LONG-NAME="Short-Name">
              <TYPE>
                <DATATYPE-DEFINITION-STRING-REF>a0788043-3c29-4cdc-b656-816a1a9e111d</DATATYPE-DEFINITION-STRING-REF>
              </TYPE>
            </ATTRIBUTE-DEFINITION-STRING>
            <ATTRIBUTE-DEFINITION-STRING DESC="The Name Attribute" IDENTIFIER="dbc2b277-306d-43bc-8c8b-c61e34f3b85a" LAST-CHANGE="2022-01-10T09:24:18.8995922Z" LONG-NAME="Name">
              <TYPE>
                <DATATYPE-DEFINITION-STRING-REF>a0788043-3c29-4cdc-b656-816a1a9e111d</DATATYPE-DEFINITION-STRING-REF>
              </TYPE>
            </ATTRIBUTE-DEFINITION-STRING>
            <ATTRIBUTE-DEFINITION-STRING DESC="The Categories Attribute" IDENTIFIER="23a0cf93-dc4f-46d1-8e2d-abd1d41ff99b" LAST-CHANGE="2022-01-10T09:24:18.8995922Z" LONG-NAME="Categories">
              <TYPE>
                <DATATYPE-DEFINITION-STRING-REF>a0788043-3c29-4cdc-b656-816a1a9e111d</DATATYPE-DEFINITION-STRING-REF>
              </TYPE>
            </ATTRIBUTE-DEFINITION-STRING>
            <ATTRIBUTE-DEFINITION-STRING DESC="The Requirement Text Attribute Definition" IDENTIFIER="7e5f54ee-02ad-484b-86cd-38aedf0fca94" LAST-CHANGE="2022-01-10T09:24:18.8995922Z" LONG-NAME="Requirement Text">
              <TYPE>
                <DATATYPE-DEFINITION-STRING-REF>a0788043-3c29-4cdc-b656-816a1a9e111d</DATATYPE-DEFINITION-STRING-REF>
              </TYPE>
            </ATTRIBUTE-DEFINITION-STRING>
            <ATTRIBUTE-DEFINITION-BOOLEAN DESC="The IsDeprecated Attribute Definition" IDENTIFIER="08311e37-6e02-484c-af09-f5292c48545b" LAST-CHANGE="2022-01-10T10:24:18.8995922+01:00" LONG-NAME="IsDeprecated">
              <TYPE>
                <DATATYPE-DEFINITION-BOOLEAN-REF>cf78e807-a8af-4816-aa0f-c7b9e7ec1520</DATATYPE-DEFINITION-BOOLEAN-REF>
              </TYPE>
            </ATTRIBUTE-DEFINITION-BOOLEAN>
            <ATTRIBUTE-DEFINITION-BOOLEAN DESC="-" IDENTIFIER="4ca988dd-df37-4f27-928c-1bf3ba7fbe83" LAST-CHANGE="2022-01-10T10:24:18.8995922+01:00">
              <TYPE>
                <DATATYPE-DEFINITION-BOOLEAN-REF>9b2e4528-dcb9-4429-841b-f0b840b15e13</DATATYPE-DEFINITION-BOOLEAN-REF>
              </TYPE>
            </ATTRIBUTE-DEFINITION-BOOLEAN>
          </SPEC-ATTRIBUTES>
        </SPEC-OBJECT-TYPE>
        <SPEC-RELATION-TYPE DESC="BinaryRelationship" IDENTIFIER="f97ee782-72eb-4c38-b917-404b83d2bb84" LAST-CHANGE="2022-01-10T09:24:18.9025916Z" LONG-NAME="BinaryRelationship">
          <SPEC-ATTRIBUTES>
            <ATTRIBUTE-DEFINITION-STRING DESC="The Short-Name Attribute" IDENTIFIER="b6948879-a3d5-48ae-886b-3b4fe3d1fdf9" LAST-CHANGE="2022-01-10T09:24:18.9025916Z" LONG-NAME="Short-Name">
              <TYPE>
                <DATATYPE-DEFINITION-STRING-REF>a0788043-3c29-4cdc-b656-816a1a9e111d</DATATYPE-DEFINITION-STRING-REF>
              </TYPE>
            </ATTRIBUTE-DEFINITION-STRING>
            <ATTRIBUTE-DEFINITION-STRING DESC="The Name Attribute" IDENTIFIER="21210e28-fa40-456d-b4ce-c37efef448a2" LAST-CHANGE="2022-01-10T09:24:18.9025916Z" LONG-NAME="Name">
              <TYPE>
                <DATATYPE-DEFINITION-STRING-REF>a0788043-3c29-4cdc-b656-816a1a9e111d</DATATYPE-DEFINITION-STRING-REF>
              </TYPE>
            </ATTRIBUTE-DEFINITION-STRING>
            <ATTRIBUTE-DEFINITION-STRING DESC="The Categories Attribute" IDENTIFIER="9f900a32-c473-4d59-8d6c-603ed113e042" LAST-CHANGE="2022-01-10T09:24:18.9025916Z" LONG-NAME="Categories">
              <TYPE>
                <DATATYPE-DEFINITION-STRING-REF>a0788043-3c29-4cdc-b656-816a1a9e111d</DATATYPE-DEFINITION-STRING-REF>
              </TYPE>
            </ATTRIBUTE-DEFINITION-STRING>
          </SPEC-ATTRIBUTES>
        </SPEC-RELATION-TYPE>
        <RELATION-GROUP-TYPE DESC="BinaryRelationship" IDENTIFIER="0939449c-6dd0-4bbd-9321-272c44b964f4" LAST-CHANGE="2022-01-10T09:24:18.9045407Z" LONG-NAME="BinaryRelationship">
          <SPEC-ATTRIBUTES>
            <ATTRIBUTE-DEFINITION-STRING DESC="The Short-Name Attribute" IDENTIFIER="3eed42f9-d7cf-4993-9a32-bd37e7e03325" LAST-CHANGE="2022-01-10T09:24:18.9045407Z" LONG-NAME="Short-Name">
              <TYPE>
                <DATATYPE-DEFINITION-STRING-REF>a0788043-3c29-4cdc-b656-816a1a9e111d</DATATYPE-DEFINITION-STRING-REF>
              </TYPE>
            </ATTRIBUTE-DEFINITION-STRING>
            <ATTRIBUTE-DEFINITION-STRING DESC="The Name Attribute" IDENTIFIER="216b3d85-04e1-4113-954b-c108a7b2735a" LAST-CHANGE="2022-01-10T09:24:18.9045407Z" LONG-NAME="Name">
              <TYPE>
                <DATATYPE-DEFINITION-STRING-REF>a0788043-3c29-4cdc-b656-816a1a9e111d</DATATYPE-DEFINITION-STRING-REF>
              </TYPE>
            </ATTRIBUTE-DEFINITION-STRING>
            <ATTRIBUTE-DEFINITION-STRING DESC="The Categories Attribute" IDENTIFIER="eabf74d0-8c75-4b3d-9cc7-09f563e401f3" LAST-CHANGE="2022-01-10T09:24:18.9045407Z" LONG-NAME="Categories">
              <TYPE>
                <DATATYPE-DEFINITION-STRING-REF>a0788043-3c29-4cdc-b656-816a1a9e111d</DATATYPE-DEFINITION-STRING-REF>
              </TYPE>
            </ATTRIBUTE-DEFINITION-STRING>
          </SPEC-ATTRIBUTES>
        </RELATION-GROUP-TYPE>
      </SPEC-TYPES>
      <SPEC-OBJECTS>
        <SPEC-OBJECT IDENTIFIER="8216aaa7-dae7-4d42-8c52-36522a285ad8" LAST-CHANGE="2022-01-10T09:24:18.9005534Z">
          <VALUES>
            <ATTRIBUTE-VALUE-STRING THE-VALUE="">
              <DEFINITION>
                <ATTRIBUTE-DEFINITION-STRING-REF>25bdbfa1-7c34-4957-86d8-f60b0bae1271</ATTRIBUTE-DEFINITION-STRING-REF>
              </DEFINITION>
            </ATTRIBUTE-VALUE-STRING>
            <ATTRIBUTE-VALUE-STRING THE-VALUE="">
              <DEFINITION>
                <ATTRIBUTE-DEFINITION-STRING-REF>44141c10-7c6f-463a-8f51-d195bf21d564</ATTRIBUTE-DEFINITION-STRING-REF>
              </DEFINITION>
            </ATTRIBUTE-VALUE-STRING>
            <ATTRIBUTE-VALUE-STRING THE-VALUE="reqcat">
              <DEFINITION>
                <ATTRIBUTE-DEFINITION-STRING-REF>1ac69cba-68c9-4fd3-858a-fd0466a86a5d</ATTRIBUTE-DEFINITION-STRING-REF>
              </DEFINITION>
            </ATTRIBUTE-VALUE-STRING>
            <ATTRIBUTE-VALUE-BOOLEAN THE-VALUE="true">
              <DEFINITION>
                <ATTRIBUTE-DEFINITION-BOOLEAN-REF>6528c6b6-e10d-4170-b003-2940dfaf7ae8</ATTRIBUTE-DEFINITION-BOOLEAN-REF>
              </DEFINITION>
            </ATTRIBUTE-VALUE-BOOLEAN>
            <ATTRIBUTE-VALUE-STRING THE-VALUE="def0">
              <DEFINITION>
                <ATTRIBUTE-DEFINITION-STRING-REF>7dd4fecf-4848-49b5-8f6d-5366bbc35491</ATTRIBUTE-DEFINITION-STRING-REF>
              </DEFINITION>
            </ATTRIBUTE-VALUE-STRING>
            <ATTRIBUTE-VALUE-BOOLEAN THE-VALUE="false">
              <DEFINITION>
                <ATTRIBUTE-DEFINITION-BOOLEAN-REF>58535613-e8d1-4884-a96c-c226680ed04a</ATTRIBUTE-DEFINITION-BOOLEAN-REF>
              </DEFINITION>
            </ATTRIBUTE-VALUE-BOOLEAN>
          </VALUES>
          <TYPE>
            <SPEC-OBJECT-TYPE-REF>aed25a8c-2542-4d63-8554-c35339b6a343</SPEC-OBJECT-TYPE-REF>
          </TYPE>
        </SPEC-OBJECT>
        <SPEC-OBJECT IDENTIFIER="e029d7e0-b58b-4e50-8637-1301e58948f4" LAST-CHANGE="2022-01-10T09:24:18.9015903Z">
          <VALUES>
            <ATTRIBUTE-VALUE-STRING THE-VALUE="">
              <DEFINITION>
                <ATTRIBUTE-DEFINITION-STRING-REF>526d8c4a-f1a2-46c1-a561-183d65d42a08</ATTRIBUTE-DEFINITION-STRING-REF>
              </DEFINITION>
            </ATTRIBUTE-VALUE-STRING>
            <ATTRIBUTE-VALUE-STRING THE-VALUE="">
              <DEFINITION>
                <ATTRIBUTE-DEFINITION-STRING-REF>6bf9b5ae-c23a-4499-998f-691e3533dde5</ATTRIBUTE-DEFINITION-STRING-REF>
              </DEFINITION>
            </ATTRIBUTE-VALUE-STRING>
            <ATTRIBUTE-VALUE-STRING THE-VALUE="reqcat">
              <DEFINITION>
                <ATTRIBUTE-DEFINITION-STRING-REF>13b519fe-1bac-4d76-96a3-1f34a1a31b29</ATTRIBUTE-DEFINITION-STRING-REF>
              </DEFINITION>
            </ATTRIBUTE-VALUE-STRING>
            <ATTRIBUTE-VALUE-BOOLEAN THE-VALUE="true">
              <DEFINITION>
                <ATTRIBUTE-DEFINITION-BOOLEAN-REF>923d214a-e31b-42fb-8ae7-7acc5067de99</ATTRIBUTE-DEFINITION-BOOLEAN-REF>
              </DEFINITION>
            </ATTRIBUTE-VALUE-BOOLEAN>
            <ATTRIBUTE-VALUE-STRING THE-VALUE="def1">
              <DEFINITION>
                <ATTRIBUTE-DEFINITION-STRING-REF>e0a57b4f-e2a1-4597-8b6c-03d91a493450</ATTRIBUTE-DEFINITION-STRING-REF>
              </DEFINITION>
            </ATTRIBUTE-VALUE-STRING>
            <ATTRIBUTE-VALUE-BOOLEAN THE-VALUE="false">
              <DEFINITION>
                <ATTRIBUTE-DEFINITION-BOOLEAN-REF>a63fdc2f-4958-44ac-bb18-1cc67e4be64f</ATTRIBUTE-DEFINITION-BOOLEAN-REF>
              </DEFINITION>
            </ATTRIBUTE-VALUE-BOOLEAN>
          </VALUES>
          <TYPE>
            <SPEC-OBJECT-TYPE-REF>dcfb10da-c1ae-4dc4-904c-1c12b0d0647f</SPEC-OBJECT-TYPE-REF>
          </TYPE>
        </SPEC-OBJECT>
        <SPEC-OBJECT IDENTIFIER="1cb13a3d-9774-4703-84f4-2937b54782b9" LAST-CHANGE="2022-01-10T09:24:18.9015903Z">
          <VALUES>
            <ATTRIBUTE-VALUE-STRING THE-VALUE="">
              <DEFINITION>
                <ATTRIBUTE-DEFINITION-STRING-REF>94a83ce4-eac5-4b9f-8e50-0fdb3d61c47e</ATTRIBUTE-DEFINITION-STRING-REF>
              </DEFINITION>
            </ATTRIBUTE-VALUE-STRING>
            <ATTRIBUTE-VALUE-STRING THE-VALUE="">
              <DEFINITION>
                <ATTRIBUTE-DEFINITION-STRING-REF>196ddc91-515d-4505-8b84-4766e7fa1494</ATTRIBUTE-DEFINITION-STRING-REF>
              </DEFINITION>
            </ATTRIBUTE-VALUE-STRING>
            <ATTRIBUTE-VALUE-STRING THE-VALUE="reqcat">
              <DEFINITION>
                <ATTRIBUTE-DEFINITION-STRING-REF>5deaa9c8-276c-45c5-9ce1-0a3bf50885a3</ATTRIBUTE-DEFINITION-STRING-REF>
              </DEFINITION>
            </ATTRIBUTE-VALUE-STRING>
            <ATTRIBUTE-VALUE-BOOLEAN THE-VALUE="true">
              <DEFINITION>
                <ATTRIBUTE-DEFINITION-BOOLEAN-REF>ced1aa61-c151-476a-aada-78de522bc33e</ATTRIBUTE-DEFINITION-BOOLEAN-REF>
              </DEFINITION>
            </ATTRIBUTE-VALUE-BOOLEAN>
            <ATTRIBUTE-VALUE-STRING THE-VALUE="def11">
              <DEFINITION>
                <ATTRIBUTE-DEFINITION-STRING-REF>052c30a1-7ab1-4bd3-957c-a951b03a4256</ATTRIBUTE-DEFINITION-STRING-REF>
              </DEFINITION>
            </ATTRIBUTE-VALUE-STRING>
            <ATTRIBUTE-VALUE-BOOLEAN THE-VALUE="false">
              <DEFINITION>
                <ATTRIBUTE-DEFINITION-BOOLEAN-REF>fa6b0289-94f9-470e-958f-3ca1a700038f</ATTRIBUTE-DEFINITION-BOOLEAN-REF>
              </DEFINITION>
            </ATTRIBUTE-VALUE-BOOLEAN>
          </VALUES>
          <TYPE>
            <SPEC-OBJECT-TYPE-REF>5e3b473a-588b-41d2-ab31-7235efffce01</SPEC-OBJECT-TYPE-REF>
          </TYPE>
        </SPEC-OBJECT>
        <SPEC-OBJECT IDENTIFIER="d80679bd-d998-4d87-8ddd-800751811843" LAST-CHANGE="2022-01-10T09:24:18.9015903Z">
          <VALUES>
            <ATTRIBUTE-VALUE-STRING THE-VALUE="">
              <DEFINITION>
                <ATTRIBUTE-DEFINITION-STRING-REF>c71bcd70-44e9-4ba7-b5a2-c6acbfd9dfea</ATTRIBUTE-DEFINITION-STRING-REF>
              </DEFINITION>
            </ATTRIBUTE-VALUE-STRING>
            <ATTRIBUTE-VALUE-STRING THE-VALUE="">
              <DEFINITION>
                <ATTRIBUTE-DEFINITION-STRING-REF>dbc2b277-306d-43bc-8c8b-c61e34f3b85a</ATTRIBUTE-DEFINITION-STRING-REF>
              </DEFINITION>
            </ATTRIBUTE-VALUE-STRING>
            <ATTRIBUTE-VALUE-STRING THE-VALUE="reqcat">
              <DEFINITION>
                <ATTRIBUTE-DEFINITION-STRING-REF>23a0cf93-dc4f-46d1-8e2d-abd1d41ff99b</ATTRIBUTE-DEFINITION-STRING-REF>
              </DEFINITION>
            </ATTRIBUTE-VALUE-STRING>
            <ATTRIBUTE-VALUE-BOOLEAN THE-VALUE="true">
              <DEFINITION>
                <ATTRIBUTE-DEFINITION-BOOLEAN-REF>4ca988dd-df37-4f27-928c-1bf3ba7fbe83</ATTRIBUTE-DEFINITION-BOOLEAN-REF>
              </DEFINITION>
            </ATTRIBUTE-VALUE-BOOLEAN>
            <ATTRIBUTE-VALUE-STRING THE-VALUE="def2">
              <DEFINITION>
                <ATTRIBUTE-DEFINITION-STRING-REF>7e5f54ee-02ad-484b-86cd-38aedf0fca94</ATTRIBUTE-DEFINITION-STRING-REF>
              </DEFINITION>
            </ATTRIBUTE-VALUE-STRING>
            <ATTRIBUTE-VALUE-BOOLEAN THE-VALUE="false">
              <DEFINITION>
                <ATTRIBUTE-DEFINITION-BOOLEAN-REF>08311e37-6e02-484c-af09-f5292c48545b</ATTRIBUTE-DEFINITION-BOOLEAN-REF>
              </DEFINITION>
            </ATTRIBUTE-VALUE-BOOLEAN>
          </VALUES>
          <TYPE>
            <SPEC-OBJECT-TYPE-REF>ac4d80e2-55b7-4447-8a17-f5409b712931</SPEC-OBJECT-TYPE-REF>
          </TYPE>
        </SPEC-OBJECT>
        <SPEC-OBJECT IDENTIFIER="2cc732c3-7387-4e1a-841d-5d09e2a6f660" LAST-CHANGE="2022-01-10T09:24:18.8975918Z" LONG-NAME="[Group]">
          <VALUES>
            <ATTRIBUTE-VALUE-STRING THE-VALUE="">
              <DEFINITION>
                <ATTRIBUTE-DEFINITION-STRING-REF>bd064023-6698-4691-9245-ae7f481188bd</ATTRIBUTE-DEFINITION-STRING-REF>
              </DEFINITION>
            </ATTRIBUTE-VALUE-STRING>
            <ATTRIBUTE-VALUE-STRING THE-VALUE="">
              <DEFINITION>
                <ATTRIBUTE-DEFINITION-STRING-REF>d3036868-ad6f-49cd-ab3e-011ad4305750</ATTRIBUTE-DEFINITION-STRING-REF>
              </DEFINITION>
            </ATTRIBUTE-VALUE-STRING>
            <ATTRIBUTE-VALUE-STRING THE-VALUE="-">
              <DEFINITION>
                <ATTRIBUTE-DEFINITION-STRING-REF>db8bd8d2-445b-4330-a76d-797aa23da207</ATTRIBUTE-DEFINITION-STRING-REF>
              </DEFINITION>
            </ATTRIBUTE-VALUE-STRING>
          </VALUES>
          <TYPE>
            <SPEC-OBJECT-TYPE-REF>caed1125-eab0-4778-8f33-43100e3d08b9</SPEC-OBJECT-TYPE-REF>
          </TYPE>
        </SPEC-OBJECT>
        <SPEC-OBJECT IDENTIFIER="e69620fe-87db-43ff-984c-0bc9a9466463" LAST-CHANGE="2022-01-10T09:24:18.8975918Z" LONG-NAME="[Group]">
          <VALUES>
            <ATTRIBUTE-VALUE-STRING THE-VALUE="">
              <DEFINITION>
                <ATTRIBUTE-DEFINITION-STRING-REF>bd064023-6698-4691-9245-ae7f481188bd</ATTRIBUTE-DEFINITION-STRING-REF>
              </DEFINITION>
            </ATTRIBUTE-VALUE-STRING>
            <ATTRIBUTE-VALUE-STRING THE-VALUE="">
              <DEFINITION>
                <ATTRIBUTE-DEFINITION-STRING-REF>d3036868-ad6f-49cd-ab3e-011ad4305750</ATTRIBUTE-DEFINITION-STRING-REF>
              </DEFINITION>
            </ATTRIBUTE-VALUE-STRING>
            <ATTRIBUTE-VALUE-STRING THE-VALUE="-">
              <DEFINITION>
                <ATTRIBUTE-DEFINITION-STRING-REF>db8bd8d2-445b-4330-a76d-797aa23da207</ATTRIBUTE-DEFINITION-STRING-REF>
              </DEFINITION>
            </ATTRIBUTE-VALUE-STRING>
          </VALUES>
          <TYPE>
            <SPEC-OBJECT-TYPE-REF>caed1125-eab0-4778-8f33-43100e3d08b9</SPEC-OBJECT-TYPE-REF>
          </TYPE>
        </SPEC-OBJECT>
      </SPEC-OBJECTS>
      <SPEC-RELATIONS>
        <SPEC-RELATION IDENTIFIER="01646c60-3971-4909-a179-56ef707e0ce8" LAST-CHANGE="2022-01-10T09:24:18.9035929Z" LONG-NAME=" -&gt; ">
          <VALUES>
            <ATTRIBUTE-VALUE-STRING THE-VALUE=".">
              <DEFINITION>
                <ATTRIBUTE-DEFINITION-STRING-REF>b6948879-a3d5-48ae-886b-3b4fe3d1fdf9</ATTRIBUTE-DEFINITION-STRING-REF>
              </DEFINITION>
            </ATTRIBUTE-VALUE-STRING>
            <ATTRIBUTE-VALUE-STRING THE-VALUE=" -&gt; ">
              <DEFINITION>
                <ATTRIBUTE-DEFINITION-STRING-REF>21210e28-fa40-456d-b4ce-c37efef448a2</ATTRIBUTE-DEFINITION-STRING-REF>
              </DEFINITION>
            </ATTRIBUTE-VALUE-STRING>
            <ATTRIBUTE-VALUE-STRING THE-VALUE="Derive">
              <DEFINITION>
                <ATTRIBUTE-DEFINITION-STRING-REF>9f900a32-c473-4d59-8d6c-603ed113e042</ATTRIBUTE-DEFINITION-STRING-REF>
              </DEFINITION>
            </ATTRIBUTE-VALUE-STRING>
          </VALUES>
          <TYPE>
            <SPEC-RELATION-TYPE-REF>f97ee782-72eb-4c38-b917-404b83d2bb84</SPEC-RELATION-TYPE-REF>
          </TYPE>
          <TARGET>
            <SPEC-OBJECT-REF>d80679bd-d998-4d87-8ddd-800751811843</SPEC-OBJECT-REF>
          </TARGET>
          <SOURCE>
            <SPEC-OBJECT-REF>8216aaa7-dae7-4d42-8c52-36522a285ad8</SPEC-OBJECT-REF>
          </SOURCE>
        </SPEC-RELATION>
        <SPEC-RELATION IDENTIFIER="6c4603e3-dce9-408b-9b15-60e4a49d800c" LAST-CHANGE="2022-01-10T09:24:18.9035929Z" LONG-NAME=" -&gt; ">
          <VALUES>
            <ATTRIBUTE-VALUE-STRING THE-VALUE=".">
              <DEFINITION>
                <ATTRIBUTE-DEFINITION-STRING-REF>b6948879-a3d5-48ae-886b-3b4fe3d1fdf9</ATTRIBUTE-DEFINITION-STRING-REF>
              </DEFINITION>
            </ATTRIBUTE-VALUE-STRING>
            <ATTRIBUTE-VALUE-STRING THE-VALUE=" -&gt; ">
              <DEFINITION>
                <ATTRIBUTE-DEFINITION-STRING-REF>21210e28-fa40-456d-b4ce-c37efef448a2</ATTRIBUTE-DEFINITION-STRING-REF>
              </DEFINITION>
            </ATTRIBUTE-VALUE-STRING>
            <ATTRIBUTE-VALUE-STRING THE-VALUE="Derive">
              <DEFINITION>
                <ATTRIBUTE-DEFINITION-STRING-REF>9f900a32-c473-4d59-8d6c-603ed113e042</ATTRIBUTE-DEFINITION-STRING-REF>
              </DEFINITION>
            </ATTRIBUTE-VALUE-STRING>
          </VALUES>
          <TYPE>
            <SPEC-RELATION-TYPE-REF>f97ee782-72eb-4c38-b917-404b83d2bb84</SPEC-RELATION-TYPE-REF>
          </TYPE>
          <TARGET>
            <SPEC-OBJECT-REF>8216aaa7-dae7-4d42-8c52-36522a285ad8</SPEC-OBJECT-REF>
          </TARGET>
          <SOURCE>
            <SPEC-OBJECT-REF>e029d7e0-b58b-4e50-8637-1301e58948f4</SPEC-OBJECT-REF>
          </SOURCE>
        </SPEC-RELATION>
        <SPEC-RELATION IDENTIFIER="dfe5d55b-532f-4ba8-a032-586c1bb68b44" LAST-CHANGE="2022-01-10T09:24:18.9035929Z" LONG-NAME=" -&gt; ">
          <VALUES>
            <ATTRIBUTE-VALUE-STRING THE-VALUE=".">
              <DEFINITION>
                <ATTRIBUTE-DEFINITION-STRING-REF>b6948879-a3d5-48ae-886b-3b4fe3d1fdf9</ATTRIBUTE-DEFINITION-STRING-REF>
              </DEFINITION>
            </ATTRIBUTE-VALUE-STRING>
            <ATTRIBUTE-VALUE-STRING THE-VALUE=" -&gt; ">
              <DEFINITION>
                <ATTRIBUTE-DEFINITION-STRING-REF>21210e28-fa40-456d-b4ce-c37efef448a2</ATTRIBUTE-DEFINITION-STRING-REF>
              </DEFINITION>
            </ATTRIBUTE-VALUE-STRING>
            <ATTRIBUTE-VALUE-STRING THE-VALUE="Derive">
              <DEFINITION>
                <ATTRIBUTE-DEFINITION-STRING-REF>9f900a32-c473-4d59-8d6c-603ed113e042</ATTRIBUTE-DEFINITION-STRING-REF>
              </DEFINITION>
            </ATTRIBUTE-VALUE-STRING>
          </VALUES>
          <TYPE>
            <SPEC-RELATION-TYPE-REF>f97ee782-72eb-4c38-b917-404b83d2bb84</SPEC-RELATION-TYPE-REF>
          </TYPE>
          <TARGET>
            <SPEC-OBJECT-REF>e029d7e0-b58b-4e50-8637-1301e58948f4</SPEC-OBJECT-REF>
          </TARGET>
          <SOURCE>
            <SPEC-OBJECT-REF>1cb13a3d-9774-4703-84f4-2937b54782b9</SPEC-OBJECT-REF>
          </SOURCE>
        </SPEC-RELATION>
      </SPEC-RELATIONS>
      <SPECIFICATIONS>
        <SPECIFICATION IDENTIFIER="7ee35944-c5aa-4b97-9d18-4a18457a129a" LAST-CHANGE="2022-01-10T09:24:18.8945401Z">
          <VALUES>
            <ATTRIBUTE-VALUE-STRING THE-VALUE="">
              <DEFINITION>
                <ATTRIBUTE-DEFINITION-STRING-REF>4e508b19-4c5d-408d-a8f1-c465b34714f6</ATTRIBUTE-DEFINITION-STRING-REF>
              </DEFINITION>
            </ATTRIBUTE-VALUE-STRING>
            <ATTRIBUTE-VALUE-STRING THE-VALUE="">
              <DEFINITION>
                <ATTRIBUTE-DEFINITION-STRING-REF>466dbc5f-18a6-433e-b2c4-46f82fc5a360</ATTRIBUTE-DEFINITION-STRING-REF>
              </DEFINITION>
            </ATTRIBUTE-VALUE-STRING>
            <ATTRIBUTE-VALUE-STRING THE-VALUE="speccat">
              <DEFINITION>
                <ATTRIBUTE-DEFINITION-STRING-REF>01fd8f87-b4d3-421b-9419-ad4b46fa6a0d</ATTRIBUTE-DEFINITION-STRING-REF>
              </DEFINITION>
            </ATTRIBUTE-VALUE-STRING>
            <ATTRIBUTE-VALUE-BOOLEAN THE-VALUE="false">
              <DEFINITION>
                <ATTRIBUTE-DEFINITION-BOOLEAN-REF>ee2625f8-c6d5-4543-a81d-b949aefd0d33</ATTRIBUTE-DEFINITION-BOOLEAN-REF>
              </DEFINITION>
            </ATTRIBUTE-VALUE-BOOLEAN>
          </VALUES>
          <TYPE>
            <SPECIFICATION-TYPE-REF>a2502760-9a0d-47c3-85b8-eaade10bd657</SPECIFICATION-TYPE-REF>
          </TYPE>
          <CHILDREN>
            <SPEC-HIERARCHY IDENTIFIER="0f7333d2-a89c-42d3-af1b-86ede567fb56" LAST-CHANGE="2022-01-10T09:24:18.9055911Z">
              <OBJECT>
                <SPEC-OBJECT-REF>e69620fe-87db-43ff-984c-0bc9a9466463</SPEC-OBJECT-REF>
              </OBJECT>
              <CHILDREN>
                <SPEC-HIERARCHY IDENTIFIER="0a1119f7-2a39-4a4b-b1a4-3e59fadcc41d" LAST-CHANGE="2022-01-10T09:24:18.9055911Z">
                  <OBJECT>
                    <SPEC-OBJECT-REF>2cc732c3-7387-4e1a-841d-5d09e2a6f660</SPEC-OBJECT-REF>
                  </OBJECT>
                  <CHILDREN>
                    <SPEC-HIERARCHY IDENTIFIER="026f68b6-878b-4e50-a044-9618a9e67eb9" LAST-CHANGE="2022-01-10T09:24:18.9055911Z">
                      <OBJECT>
                        <SPEC-OBJECT-REF>1cb13a3d-9774-4703-84f4-2937b54782b9</SPEC-OBJECT-REF>
                      </OBJECT>
                    </SPEC-HIERARCHY>
                  </CHILDREN>
                </SPEC-HIERARCHY>
                <SPEC-HIERARCHY IDENTIFIER="fe5792f6-626d-4226-95d4-50e3ea64de0e" LAST-CHANGE="2022-01-10T09:24:18.9055911Z">
                  <OBJECT>
                    <SPEC-OBJECT-REF>e029d7e0-b58b-4e50-8637-1301e58948f4</SPEC-OBJECT-REF>
                  </OBJECT>
                </SPEC-HIERARCHY>
              </CHILDREN>
            </SPEC-HIERARCHY>
            <SPEC-HIERARCHY IDENTIFIER="fcb05852-01af-46ae-b92b-a4cf9fbf5e1c" LAST-CHANGE="2022-01-10T09:24:18.9065407Z">
              <OBJECT>
                <SPEC-OBJECT-REF>8216aaa7-dae7-4d42-8c52-36522a285ad8</SPEC-OBJECT-REF>
              </OBJECT>
            </SPEC-HIERARCHY>
          </CHILDREN>
        </SPECIFICATION>
        <SPECIFICATION IDENTIFIER="875bdd60-322c-4db9-9922-f39fbf9160df" LAST-CHANGE="2022-01-10T09:24:18.8955393Z">
          <VALUES>
            <ATTRIBUTE-VALUE-STRING THE-VALUE="">
              <DEFINITION>
                <ATTRIBUTE-DEFINITION-STRING-REF>4e508b19-4c5d-408d-a8f1-c465b34714f6</ATTRIBUTE-DEFINITION-STRING-REF>
              </DEFINITION>
            </ATTRIBUTE-VALUE-STRING>
            <ATTRIBUTE-VALUE-STRING THE-VALUE="">
              <DEFINITION>
                <ATTRIBUTE-DEFINITION-STRING-REF>466dbc5f-18a6-433e-b2c4-46f82fc5a360</ATTRIBUTE-DEFINITION-STRING-REF>
              </DEFINITION>
            </ATTRIBUTE-VALUE-STRING>
            <ATTRIBUTE-VALUE-STRING THE-VALUE="speccat">
              <DEFINITION>
                <ATTRIBUTE-DEFINITION-STRING-REF>01fd8f87-b4d3-421b-9419-ad4b46fa6a0d</ATTRIBUTE-DEFINITION-STRING-REF>
              </DEFINITION>
            </ATTRIBUTE-VALUE-STRING>
            <ATTRIBUTE-VALUE-BOOLEAN THE-VALUE="false">
              <DEFINITION>
                <ATTRIBUTE-DEFINITION-BOOLEAN-REF>ee2625f8-c6d5-4543-a81d-b949aefd0d33</ATTRIBUTE-DEFINITION-BOOLEAN-REF>
              </DEFINITION>
            </ATTRIBUTE-VALUE-BOOLEAN>
          </VALUES>
          <TYPE>
            <SPECIFICATION-TYPE-REF>a2502760-9a0d-47c3-85b8-eaade10bd657</SPECIFICATION-TYPE-REF>
          </TYPE>
          <CHILDREN>
            <SPEC-HIERARCHY IDENTIFIER="67184870-fa2d-4ff2-a2d0-4bd33419fa90" LAST-CHANGE="2022-01-10T09:24:18.9065407Z">
              <OBJECT>
                <SPEC-OBJECT-REF>d80679bd-d998-4d87-8ddd-800751811843</SPEC-OBJECT-REF>
              </OBJECT>
            </SPEC-HIERARCHY>
          </CHILDREN>
        </SPECIFICATION>
        <SPECIFICATION IDENTIFIER="1bbc4e2c-6b24-42a0-a1d5-5bc0f901789c" LAST-CHANGE="2022-01-10T09:24:18.8955393Z">
          <VALUES>
            <ATTRIBUTE-VALUE-STRING THE-VALUE="">
              <DEFINITION>
                <ATTRIBUTE-DEFINITION-STRING-REF>4e508b19-4c5d-408d-a8f1-c465b34714f6</ATTRIBUTE-DEFINITION-STRING-REF>
              </DEFINITION>
            </ATTRIBUTE-VALUE-STRING>
            <ATTRIBUTE-VALUE-STRING THE-VALUE="">
              <DEFINITION>
                <ATTRIBUTE-DEFINITION-STRING-REF>466dbc5f-18a6-433e-b2c4-46f82fc5a360</ATTRIBUTE-DEFINITION-STRING-REF>
              </DEFINITION>
            </ATTRIBUTE-VALUE-STRING>
            <ATTRIBUTE-VALUE-STRING THE-VALUE="speccat">
              <DEFINITION>
                <ATTRIBUTE-DEFINITION-STRING-REF>01fd8f87-b4d3-421b-9419-ad4b46fa6a0d</ATTRIBUTE-DEFINITION-STRING-REF>
              </DEFINITION>
            </ATTRIBUTE-VALUE-STRING>
            <ATTRIBUTE-VALUE-BOOLEAN THE-VALUE="true">
              <DEFINITION>
                <ATTRIBUTE-DEFINITION-BOOLEAN-REF>ee2625f8-c6d5-4543-a81d-b949aefd0d33</ATTRIBUTE-DEFINITION-BOOLEAN-REF>
              </DEFINITION>
            </ATTRIBUTE-VALUE-BOOLEAN>
          </VALUES>
          <TYPE>
            <SPECIFICATION-TYPE-REF>a2502760-9a0d-47c3-85b8-eaade10bd657</SPECIFICATION-TYPE-REF>
          </TYPE>
        </SPECIFICATION>
      </SPECIFICATIONS>
      <SPEC-RELATION-GROUPS>
        <RELATION-GROUP IDENTIFIER="5d83f9e8-acac-4204-a6ac-1c2d354f3faa" LAST-CHANGE="2022-01-10T09:24:18.9055911Z" LONG-NAME=" -&gt; ">
          <VALUES>
            <ATTRIBUTE-VALUE-STRING THE-VALUE=".">
              <DEFINITION>
                <ATTRIBUTE-DEFINITION-STRING-REF>3eed42f9-d7cf-4993-9a32-bd37e7e03325</ATTRIBUTE-DEFINITION-STRING-REF>
              </DEFINITION>
            </ATTRIBUTE-VALUE-STRING>
            <ATTRIBUTE-VALUE-STRING THE-VALUE=" -&gt; ">
              <DEFINITION>
                <ATTRIBUTE-DEFINITION-STRING-REF>216b3d85-04e1-4113-954b-c108a7b2735a</ATTRIBUTE-DEFINITION-STRING-REF>
              </DEFINITION>
            </ATTRIBUTE-VALUE-STRING>
            <ATTRIBUTE-VALUE-STRING THE-VALUE="SpecLink">
              <DEFINITION>
                <ATTRIBUTE-DEFINITION-STRING-REF>eabf74d0-8c75-4b3d-9cc7-09f563e401f3</ATTRIBUTE-DEFINITION-STRING-REF>
              </DEFINITION>
            </ATTRIBUTE-VALUE-STRING>
          </VALUES>
          <TYPE>
            <RELATION-GROUP-TYPE-REF>0939449c-6dd0-4bbd-9321-272c44b964f4</RELATION-GROUP-TYPE-REF>
          </TYPE>
          <SOURCE-SPECIFICATION>
            <SPECIFICATION-REF>7ee35944-c5aa-4b97-9d18-4a18457a129a</SPECIFICATION-REF>
          </SOURCE-SPECIFICATION>
          <TARGET-SPECIFICATION>
            <SPECIFICATION-REF>875bdd60-322c-4db9-9922-f39fbf9160df</SPECIFICATION-REF>
          </TARGET-SPECIFICATION>
          <SPEC-RELATIONS>
            <SPEC-RELATION-REF>01646c60-3971-4909-a179-56ef707e0ce8</SPEC-RELATION-REF>
          </SPEC-RELATIONS>
        </RELATION-GROUP>
      </SPEC-RELATION-GROUPS>
    </REQ-IF-CONTENT>
  </CORE-CONTENT>
</REQ-IF>